{"date" : "1998.09.18.FRI<br>PM 8:00",
"date_disp_flag" : "1",
"free" : "",
"biko" :"",
"biko2" :"",
"onair" : "",
"kakutei" : "1",
"data" : [
{
"artists_name_disp" : "the brilliant green",
"artists_name_img": "",
"music_name_disp" : "冷たい花",
"music_name_img" : "",
"sort": "2"
},{
"artists_name_disp" : "エレファントカシマシ",
"artists_name_img": "",
"music_name_disp" : "夢のかけら",
"music_name_img" : "",
"sort": "3"
},{
"artists_name_disp" : "サーフィス",
"artists_name_img": "",
"music_name_disp" : "ジレンマ",
"music_name_img" : "",
"sort": "4"
},{
"artists_name_disp" : "ラクリマ・クリスティー",
"artists_name_img": "",
"music_name_disp" : "未来航路",
"music_name_img" : "",
"sort": "5"
},{
"artists_name_disp" : "少年隊",
"artists_name_img": "",
"music_name_disp" : "愛と沈黙",
"music_name_img" : "",
"sort": "6"
},{
"artists_name_disp" : "内田有紀",
"artists_name_img": "",
"music_name_disp" : "ハートブレイク　スナイパー",
"music_name_img" : "",
"sort": "7"
},{
"artists_name_disp" : "鈴木あみ",
"artists_name_img": "",
"music_name_disp" : "alone in my room",
"music_name_img" : "",
"sort": "8"
},{}]}