{"date" : "1998.11.06.FRI<br>PM 8:00",
"date_disp_flag" : "1",
"free" : "",
"biko" :"",
"biko2" :"",
"onair" : "",
"kakutei" : "1",
"data" : [
{
"artists_name_disp" : "Pool bit boys",
"artists_name_img": "",
"music_name_disp" : "Venus Accident",
"music_name_img" : "",
"sort": "2"
},{
"artists_name_disp" : "SIAM SHADE",
"artists_name_img": "",
"music_name_disp" : "NEVER END",
"music_name_img" : "",
"sort": "3"
},{
"artists_name_disp" : "V6",
"artists_name_img": "",
"music_name_disp" : "over",
"music_name_img" : "",
"sort": "4"
},{
"artists_name_disp" : "スガシカオ",
"artists_name_img": "",
"music_name_disp" : "ぼくたちの日々",
"music_name_img" : "",
"sort": "5"
},{
"artists_name_disp" : "今井美樹",
"artists_name_img": "",
"music_name_disp" : "flowers",
"music_name_img" : "",
"sort": "6"
},{
"artists_name_disp" : "福山雅治",
"artists_name_img": "",
"music_name_disp" : "Peach!!",
"music_name_img" : "",
"sort": "7"
},{
"artists_name_disp" : "鈴木あみ",
"artists_name_img": "",
"music_name_disp" : "all night long",
"music_name_img" : "",
"sort": "8"
},{}]}