{"date" : "1999.01.29.FRI<br>PM 8:00",
"date_disp_flag" : "1",
"free" : "",
"biko" :"",
"biko2" :"",
"onair" : "",
"kakutei" : "1",
"data" : [
{
"artists_name_disp" : "deeps",
"artists_name_img": "",
"music_name_disp" : "Brand-New Heaven",
"music_name_img" : "",
"sort": "2"
},{
"artists_name_disp" : "Every Little Thing",
"artists_name_img": "",
"music_name_disp" : "Over and Over",
"music_name_img" : "",
"sort": "3"
},{
"artists_name_disp" : "the brilliant green",
"artists_name_img": "",
"music_name_disp" : "そのスピードで",
"music_name_img" : "",
"sort": "4"
},{
"artists_name_disp" : "TOKIO",
"artists_name_img": "",
"music_name_disp" : "一秒のOthello　～君に選ばれたい～",
"music_name_img" : "",
"sort": "5"
},{
"artists_name_disp" : "ジャニーズ Jr.",
"artists_name_img": "",
"music_name_disp" : "They Don't Care About Us",
"music_name_img" : "",
"sort": "6"
},{
"artists_name_disp" : "ジャニーズ Jr.",
"artists_name_img": "",
"music_name_disp" : "サヨナラ",
"music_name_img" : "",
"sort": "7"
},{
"artists_name_disp" : "ジャニーズ Jr.",
"artists_name_img": "",
"music_name_disp" : "明日に向かって",
"music_name_img" : "",
"sort": "8"
},{
"artists_name_disp" : "安室奈美恵",
"artists_name_img": "",
"music_name_disp" : "I HAVE NEVER SEEN",
"music_name_img" : "",
"sort": "9"
},{
"artists_name_disp" : "広末涼子",
"artists_name_img": "",
"music_name_disp" : "明日へ",
"music_name_img" : "",
"sort": "10"
},{}]}