{"date" : "2001.08.24.FRI<br>PM 8:00",
"date_disp_flag" : "1",
"free" : "",
"biko" :"",
"biko2" :"",
"onair" : "",
"kakutei" : "1",
"data" : [
{
"artists_name_disp" : "滝沢秀明 & ジャニーズ Jr.",
"artists_name_img": "",
"music_name_disp" : "Everlasting LOVE～終わりのない想い～",
"music_name_img" : "",
"sort": "2"
},{
"artists_name_disp" : "滝沢秀明 & ジャニーズ Jr.",
"artists_name_img": "",
"music_name_disp" : "circle",
"music_name_img" : "",
"sort": "3"
},{
"artists_name_disp" : "滝沢秀明 & ジャニーズ Jr.",
"artists_name_img": "",
"music_name_disp" : "Believe",
"music_name_img" : "",
"sort": "4"
},{
"artists_name_disp" : "Mr.Children",
"artists_name_img": "",
"music_name_disp" : "優しい歌",
"music_name_img" : "",
"sort": "5"
},{
"artists_name_disp" : "華原朋美",
"artists_name_img": "",
"music_name_disp" : "PRECIOUS",
"music_name_img" : "",
"sort": "6"
},{
"artists_name_disp" : "19",
"artists_name_img": "",
"music_name_disp" : "たいせつなひと",
"music_name_img" : "",
"sort": "7"
},{
"artists_name_disp" : "今井美樹",
"artists_name_img": "",
"music_name_disp" : "潮騒",
"music_name_img" : "",
"sort": "8"
},{
"artists_name_disp" : "慎吾ママ",
"artists_name_img": "",
"music_name_disp" : "慎吾ママの学園天国ー校門篇ー",
"music_name_img" : "",
"sort": "9"
},{
"artists_name_disp" : "THE ALFEE",
"artists_name_img": "",
"music_name_disp" : "Juliet",
"music_name_img" : "",
"sort": "10"
},{}]}