{"date" : "2006.09.01.FRI<br>PM 8:00",
"date_disp_flag" : "1",
"free" : "",
"biko" :"",
"biko2" :"",
"onair" : "2054",
"kakutei" : "1",
"data" : [
{
"artists_name_disp" : "関ジャニ∞",
"artists_name_img": "",
"music_name_disp" : "∞ＳＡＫＡおばちゃんＲＯＣＫ",
"music_name_img" : "",
"sort": "1"
},{
"artists_name_disp" : "木村カエラ",
"artists_name_img": "",
"music_name_disp" : "TREE CLIMBERS",
"music_name_img" : "",
"sort": "3"
},{
"artists_name_disp" : "SEAMO",
"artists_name_img": "",
"music_name_disp" : "マタアイマショウ",
"music_name_img" : "",
"sort": "6"
},{
"artists_name_disp" : "スガ シカオ",
"artists_name_img": "",
"music_name_disp" : "午後のパレード",
"music_name_img" : "",
"sort": "7"
},{
"artists_name_disp" : "スキマスイッチ",
"artists_name_img": "",
"music_name_disp" : "スフィアの羽根",
"music_name_img" : "",
"sort": "2"
},{
"artists_name_disp" : "風味堂",
"artists_name_img": "",
"music_name_disp" : "愛してる",
"music_name_img" : "",
"sort": "5"
},{
"artists_name_disp" : "山田 優",
"artists_name_img": "",
"music_name_disp" : "REAL YOU",
"music_name_img" : "",
"sort": "4"
},{
"artists_name_disp" : "関ジャニ∞",
"artists_name_img": "",
"music_name_disp" : "サムライブルース",
"music_name_img" : "",
"sort": "1"
},{
"artists_name_disp" : "関ジャニ∞",
"artists_name_img": "",
"music_name_disp" : "プロ∞ペラ",
"music_name_img" : "",
"sort": "1"
},{}]}