{"date" : "2008.03.14.FRI<br>PM 8:00",
"date_disp_flag" : "1",
"free" : "",
"biko" :"",
"biko2" :"",
"onair" : "2050",
"kakutei" : "1",
"data" : [
{
"artists_name_disp" : "THE ALFEE",
"artists_name_img": "",
"music_name_disp" : "Lifetime Love",
"music_name_img" : "",
"sort": "7"
},{
"artists_name_disp" : "関ジャニ∞",
"artists_name_img": "",
"music_name_disp" : "ワッハッハー",
"music_name_img" : "",
"sort": "2"
},{
"artists_name_disp" : "TERIYAKI BOYZ&reg;",
"artists_name_img": "",
"music_name_disp" : "ZOCK ON! feat.Pharrell",
"music_name_img" : "",
"sort": "5"
},{
"artists_name_disp" : "中島美嘉",
"artists_name_img": "",
"music_name_disp" : "SAKURA～花霞～",
"music_name_img" : "",
"sort": "3"
},{
"artists_name_disp" : "平井堅",
"artists_name_img": "",
"music_name_disp" : "写真",
"music_name_img" : "",
"sort": "6"
},{
"artists_name_disp" : "FUNKY MONKEY BABYS",
"artists_name_img": "",
"music_name_disp" : "旅立ち",
"music_name_img" : "",
"sort": "1"
},{
"artists_name_disp" : "山崎まさよし",
"artists_name_img": "",
"music_name_disp" : "真夜中のBoon Boon",
"music_name_img" : "",
"sort": "4"
},{}]}