{"date" : "2012.01.20.FRI<br>PM 8:00",
"date_disp_flag" : "1",
"free" : "",
"biko" :"",
"biko2" :"",
"onair" : "2045",
"kakutei" : "1",
"data" : [
{
"artists_name_disp" : "いきものがかり",
"artists_name_img": "",
"music_name_disp" : "いつだって僕らは",
"music_name_img" : "",
"sort": "2"
},{
"artists_name_disp" : "JUN SKY WALKER(S)",
"artists_name_img": "",
"music_name_disp" : "START",
"music_name_img" : "",
"sort": "4"
},{
"artists_name_disp" : "Sexy Zone",
"artists_name_img": "",
"music_name_disp" : "Knock! Knock!! Knock!!!<br>I see the light～僕たちのステージ～<br>Sexy Zone",
"music_name_img" : "",
"sort": "3"
},{
"artists_name_disp" : "東京事変",
"artists_name_img": "",
"music_name_disp" : "今夜はから騒ぎ<br>群青日和",
"music_name_img" : "",
"sort": "5"
},{
"artists_name_disp" : "BIGBANG",
"artists_name_img": "",
"music_name_disp" : "TONIGHT",
"music_name_img" : "",
"sort": "1"
},{}]}