{"date" : "2012.10.05.FRI<br>PM 8:00",
"date_disp_flag" : "1",
"free" : "",
"biko" :"",
"biko2" :"",
"onair" : "2045",
"kakutei" : "1",
"data" : [
{
"artists_name_disp" : "嵐",
"artists_name_img": "",
"music_name_disp" : "証<br>ワイルド アット ハート",
"music_name_img" : "",
"sort": "6"
},{
"artists_name_disp" : "AKB48",
"artists_name_img": "",
"music_name_disp" : "UZA",
"music_name_img" : "",
"sort": "5"
},{
"artists_name_disp" : "きゃりーぱみゅぱみゅ",
"artists_name_img": "",
"music_name_disp" : "ファッションモンスター",
"music_name_img" : "",
"sort": "1"
},{
"artists_name_disp" : "Superfly",
"artists_name_img": "",
"music_name_disp" : "Force",
"music_name_img" : "",
"sort": "3"
},{
"artists_name_disp" : "Sexy Zone",
"artists_name_img": "",
"music_name_disp" : "Sexy Summerに雪が降る",
"music_name_img" : "",
"sort": "2"
},{
"artists_name_disp" : "福山雅治",
"artists_name_img": "",
"music_name_disp" : "GAME<br>Beautiful life",
"music_name_img" : "",
"sort": "7"
},{
"artists_name_disp" : "ポルノグラフィティ",
"artists_name_img": "",
"music_name_disp" : "カゲボウシ",
"music_name_img" : "",
"sort": "4"
},{}]}