{"date" : "2017.09.01.FRI<br>PM 8:00",
"date_disp_flag" : "1",
"free" : "",
"biko" :"",
"biko2" :"",
"onair" : "2045",
"kakutei" : "1",
"data" : [
{
"artists_name_disp" : "AKB48",
"artists_name_img": "",
"music_name_disp" : "#好きなんだ",
"music_name_img" : "",
"sort": "4"
},{
"artists_name_disp" : "DAOKO",
"artists_name_img": "",
"music_name_disp" : "打上花火",
"music_name_img" : "",
"sort": "2"
},{
"artists_name_disp" : "TOKIO",
"artists_name_img": "",
"music_name_disp" : "クモ",
"music_name_img" : "",
"sort": "6"
},{
"artists_name_disp" : "Perfume",
"artists_name_img": "",
"music_name_disp" : "If you wanna",
"music_name_img" : "",
"sort": "5"
},{
"artists_name_disp" : "Flower",
"artists_name_img": "",
"music_name_disp" : "たいようの哀悼歌",
"music_name_img" : "",
"sort": "1"
},{
"artists_name_disp" : "ポルノグラフィティ",
"artists_name_img": "",
"music_name_disp" : "キング&クイーン",
"music_name_img" : "",
"sort": "3"
},{}]}